django_fsm/__init__.py
django_fsm/models.py
django_fsm/signals.py
django_fsm/management/__init__.py
django_fsm/management/commands/__init__.py
django_fsm/management/commands/graph_transitions.py
django_fsm-3.0.1.dist-info/LICENSE
django_fsm-3.0.1.dist-info/METADATA
django_fsm-3.0.1.dist-info/WHEEL
django_fsm-3.0.1.dist-info/top_level.txt
django_fsm-3.0.1.dist-info/RECORD
